{
  "plugin": "Lindell 69 Channel",
  "vendor": "Plugin Alliance",
  "format": "VST3",
  "path": "/Library/Audio/Plug-Ins/VST3/Lindell 69 Channel.vst3",
  "parameter_count": 44,
  "params": {
    "1": "THD",
    "2": "Gain",
    "3": "Pad",
    "4": "Unity",
    "5": "High Freq",
    "6": "High Gain",
    "7": "Mid Freq",
    "8": "Mid Gain",
    "9": "Mid Mode",
    "10": "Low Freq",
    "11": "Low Gain",
    "12": "equalizer",
    "13": "EQ Post",
    "14": "High Pass",
    "15": "Comp Mix",
    "16": "Comp High Pass Filter",
    "17": "Comp Threshold",
    "18": "Comp Ratio",
    "19": "Comp Attack",
    "20": "Comp Release",
    "21": "Comp Input",
    "22": "Comp Output",
    "23": "Comp Limit",
    "24": "Comp In",
    "25": "Comp Niveau",
    "26": "Comp Smash",
    "27": "Comp External Side Chain",
    "28": "Exp Threshold",
    "29": "Exp Range",
    "30": "Exp Attack",
    "31": "Exp Release",
    "32": "Exp Mode",
    "33": "Exp Hold",
    "34": "Exp Inverted",
    "35": "Exp External Side Chain",
    "36": "Mute",
    "37": "Phase",
    "38": "Level",
    "39": "Input Level",
    "40": "Output Level",
    "41": "TMT Channel",
    "42": "TMT Link",
    "43": "Bypass",
    "44": "Program"
  },
  "edge_cases": []
}